{
  "db": {
    "dbConfig": {
      "filename": "./db.sqlite"
    },
    "database": "sqlite3"
  },
  "graphqlCRUD": {
    "create": true,
    "update": true,
    "findAll": true,
    "find": true,
    "delete": false,
    "subCreate": false,
    "subUpdate": false,
    "subDelete": false,
    "disableGen": false
  },
  "folders": {
    "model": "./model",
    "resolvers": "./server/src/resolvers/",
    "schema": "./server/src/schema",
    "client": "./client/src/graphql",
    "migrations": "./model/migrations"
  },
  "client": true
}